{
  "player": {
    "id": 1004,
    "mlbId": 691788,
    "name": "Joe Mack",
    "slug": "joe-mack",
    "mlbTeam": "MIA",
    "position": "C",
    "teamId": null,
    "fantasyTeam": "",
    "draftRound": null,
    "overallRank": 283
  },
  "seasonTotals": {
    "gamesPlayed": 44,
    "atBats": 133,
    "hits": 34,
    "doubles": 5,
    "triples": 0,
    "homeRuns": 6,
    "totalBases": 57,
    "stolenBases": 0,
    "baseOnBalls": 10,
    "hitByPitch": 1,
    "runs": 22,
    "rbi": 22,
    "strikeouts": 35,
    "plateAppearances": 146,
    "sacBunts": 2,
    "sacFlies": 0,
    "groundIntoDoublePlay": 5,
    "groundIntoTriplePlay": 0,
    "leftOnBase": 55,
    "groundOuts": 36,
    "flyOuts": 19,
    "lineOuts": 4,
    "popOuts": 7,
    "airOuts": 30,
    "catchersInterference": 0,
    "caughtStealing": 0,
    "intentionalWalks": 0,
    "pickoffs": 0,
    "fantasyScore": 68
  },
  "games": [
    {
      "gameDate": "2026-05-04",
      "gamePk": null,
      "atBats": 3,
      "hits": 0,
      "doubles": 0,
      "triples": 0,
      "homeRuns": 0,
      "totalBases": 0,
      "stolenBases": 0,
      "baseOnBalls": 0,
      "hitByPitch": 0,
      "runs": 0,
      "rbi": 0,
      "strikeouts": 1,
      "plateAppearances": 3,
      "sacBunts": 0,
      "sacFlies": 0,
      "groundIntoDoublePlay": 0,
      "groundIntoTriplePlay": 0,
      "leftOnBase": 2,
      "groundOuts": 1,
      "flyOuts": 0,
      "lineOuts": 0,
      "popOuts": 1,
      "airOuts": 1,
      "catchersInterference": 0,
      "caughtStealing": 0,
      "intentionalWalks": 0,
      "pickoffs": 0,
      "fantasyScore": 0
    },
    {
      "gameDate": "2026-05-05",
      "gamePk": null,
      "atBats": 4,
      "hits": 2,
      "doubles": 0,
      "triples": 0,
      "homeRuns": 0,
      "totalBases": 2,
      "stolenBases": 0,
      "baseOnBalls": 0,
      "hitByPitch": 0,
      "runs": 0,
      "rbi": 1,
      "strikeouts": 1,
      "plateAppearances": 4,
      "sacBunts": 0,
      "sacFlies": 0,
      "groundIntoDoublePlay": 0,
      "groundIntoTriplePlay": 0,
      "leftOnBase": 0,
      "groundOuts": 0,
      "flyOuts": 1,
      "lineOuts": 0,
      "popOuts": 0,
      "airOuts": 1,
      "catchersInterference": 0,
      "caughtStealing": 0,
      "intentionalWalks": 0,
      "pickoffs": 0,
      "fantasyScore": 2
    },
    {
      "gameDate": "2026-05-06",
      "gamePk": null,
      "atBats": 2,
      "hits": 0,
      "doubles": 0,
      "triples": 0,
      "homeRuns": 0,
      "totalBases": 0,
      "stolenBases": 0,
      "baseOnBalls": 0,
      "hitByPitch": 0,
      "runs": 0,
      "rbi": 0,
      "strikeouts": 0,
      "plateAppearances": 2,
      "sacBunts": 0,
      "sacFlies": 0,
      "groundIntoDoublePlay": 0,
      "groundIntoTriplePlay": 0,
      "leftOnBase": 2,
      "groundOuts": 2,
      "flyOuts": 0,
      "lineOuts": 0,
      "popOuts": 0,
      "airOuts": 0,
      "catchersInterference": 0,
      "caughtStealing": 0,
      "intentionalWalks": 0,
      "pickoffs": 0,
      "fantasyScore": 0
    },
    {
      "gameDate": "2026-05-07",
      "gamePk": null,
      "atBats": 1,
      "hits": 1,
      "doubles": 1,
      "triples": 0,
      "homeRuns": 0,
      "totalBases": 2,
      "stolenBases": 0,
      "baseOnBalls": 0,
      "hitByPitch": 0,
      "runs": 1,
      "rbi": 0,
      "strikeouts": 0,
      "plateAppearances": 1,
      "sacBunts": 0,
      "sacFlies": 0,
      "groundIntoDoublePlay": 0,
      "groundIntoTriplePlay": 0,
      "leftOnBase": 0,
      "groundOuts": 0,
      "flyOuts": 0,
      "lineOuts": 0,
      "popOuts": 0,
      "airOuts": 0,
      "catchersInterference": 0,
      "caughtStealing": 0,
      "intentionalWalks": 0,
      "pickoffs": 0,
      "fantasyScore": 2
    },
    {
      "gameDate": "2026-05-08",
      "gamePk": null,
      "atBats": 3,
      "hits": 0,
      "doubles": 0,
      "triples": 0,
      "homeRuns": 0,
      "totalBases": 0,
      "stolenBases": 0,
      "baseOnBalls": 0,
      "hitByPitch": 0,
      "runs": 0,
      "rbi": 0,
      "strikeouts": 1,
      "plateAppearances": 3,
      "sacBunts": 0,
      "sacFlies": 0,
      "groundIntoDoublePlay": 0,
      "groundIntoTriplePlay": 0,
      "leftOnBase": 0,
      "groundOuts": 1,
      "flyOuts": 0,
      "lineOuts": 1,
      "popOuts": 0,
      "airOuts": 1,
      "catchersInterference": 0,
      "caughtStealing": 0,
      "intentionalWalks": 0,
      "pickoffs": 0,
      "fantasyScore": 0
    },
    {
      "gameDate": "2026-05-09",
      "gamePk": null,
      "atBats": 4,
      "hits": 2,
      "doubles": 2,
      "triples": 0,
      "homeRuns": 0,
      "totalBases": 4,
      "stolenBases": 0,
      "baseOnBalls": 0,
      "hitByPitch": 0,
      "runs": 0,
      "rbi": 0,
      "strikeouts": 1,
      "plateAppearances": 4,
      "sacBunts": 0,
      "sacFlies": 0,
      "groundIntoDoublePlay": 0,
      "groundIntoTriplePlay": 0,
      "leftOnBase": 1,
      "groundOuts": 0,
      "flyOuts": 0,
      "lineOuts": 0,
      "popOuts": 1,
      "airOuts": 1,
      "catchersInterference": 0,
      "caughtStealing": 0,
      "intentionalWalks": 0,
      "pickoffs": 0,
      "fantasyScore": 4
    },
    {
      "gameDate": "2026-05-10",
      "gamePk": null,
      "atBats": 3,
      "hits": 0,
      "doubles": 0,
      "triples": 0,
      "homeRuns": 0,
      "totalBases": 0,
      "stolenBases": 0,
      "baseOnBalls": 1,
      "hitByPitch": 0,
      "runs": 1,
      "rbi": 0,
      "strikeouts": 1,
      "plateAppearances": 4,
      "sacBunts": 0,
      "sacFlies": 0,
      "groundIntoDoublePlay": 0,
      "groundIntoTriplePlay": 0,
      "leftOnBase": 4,
      "groundOuts": 2,
      "flyOuts": 0,
      "lineOuts": 0,
      "popOuts": 0,
      "airOuts": 0,
      "catchersInterference": 0,
      "caughtStealing": 0,
      "intentionalWalks": 0,
      "pickoffs": 0,
      "fantasyScore": 1
    },
    {
      "gameDate": "2026-05-12",
      "gamePk": null,
      "atBats": 3,
      "hits": 0,
      "doubles": 0,
      "triples": 0,
      "homeRuns": 0,
      "totalBases": 0,
      "stolenBases": 0,
      "baseOnBalls": 0,
      "hitByPitch": 0,
      "runs": 0,
      "rbi": 0,
      "strikeouts": 2,
      "plateAppearances": 3,
      "sacBunts": 0,
      "sacFlies": 0,
      "groundIntoDoublePlay": 0,
      "groundIntoTriplePlay": 0,
      "leftOnBase": 0,
      "groundOuts": 1,
      "flyOuts": 0,
      "lineOuts": 0,
      "popOuts": 0,
      "airOuts": 0,
      "catchersInterference": 0,
      "caughtStealing": 0,
      "intentionalWalks": 0,
      "pickoffs": 0,
      "fantasyScore": 0
    },
    {
      "gameDate": "2026-05-13",
      "gamePk": null,
      "atBats": 4,
      "hits": 1,
      "doubles": 0,
      "triples": 0,
      "homeRuns": 0,
      "totalBases": 1,
      "stolenBases": 0,
      "baseOnBalls": 0,
      "hitByPitch": 0,
      "runs": 1,
      "rbi": 1,
      "strikeouts": 2,
      "plateAppearances": 4,
      "sacBunts": 0,
      "sacFlies": 0,
      "groundIntoDoublePlay": 0,
      "groundIntoTriplePlay": 0,
      "leftOnBase": 1,
      "groundOuts": 0,
      "flyOuts": 1,
      "lineOuts": 0,
      "popOuts": 0,
      "airOuts": 1,
      "catchersInterference": 0,
      "caughtStealing": 0,
      "intentionalWalks": 0,
      "pickoffs": 0,
      "fantasyScore": 1
    },
    {
      "gameDate": "2026-05-15",
      "gamePk": null,
      "atBats": 3,
      "hits": 0,
      "doubles": 0,
      "triples": 0,
      "homeRuns": 0,
      "totalBases": 0,
      "stolenBases": 0,
      "baseOnBalls": 0,
      "hitByPitch": 0,
      "runs": 0,
      "rbi": 0,
      "strikeouts": 2,
      "plateAppearances": 3,
      "sacBunts": 0,
      "sacFlies": 0,
      "groundIntoDoublePlay": 0,
      "groundIntoTriplePlay": 0,
      "leftOnBase": 0,
      "groundOuts": 0,
      "flyOuts": 1,
      "lineOuts": 0,
      "popOuts": 0,
      "airOuts": 1,
      "catchersInterference": 0,
      "caughtStealing": 0,
      "intentionalWalks": 0,
      "pickoffs": 0,
      "fantasyScore": 0
    },
    {
      "gameDate": "2026-05-16",
      "gamePk": null,
      "atBats": 5,
      "hits": 1,
      "doubles": 0,
      "triples": 0,
      "homeRuns": 0,
      "totalBases": 1,
      "stolenBases": 0,
      "baseOnBalls": 0,
      "hitByPitch": 0,
      "runs": 1,
      "rbi": 0,
      "strikeouts": 3,
      "plateAppearances": 5,
      "sacBunts": 0,
      "sacFlies": 0,
      "groundIntoDoublePlay": 0,
      "groundIntoTriplePlay": 0,
      "leftOnBase": 1,
      "groundOuts": 1,
      "flyOuts": 0,
      "lineOuts": 0,
      "popOuts": 0,
      "airOuts": 0,
      "catchersInterference": 0,
      "caughtStealing": 0,
      "intentionalWalks": 0,
      "pickoffs": 0,
      "fantasyScore": 1
    },
    {
      "gameDate": "2026-05-17",
      "gamePk": null,
      "atBats": 2,
      "hits": 1,
      "doubles": 0,
      "triples": 0,
      "homeRuns": 0,
      "totalBases": 1,
      "stolenBases": 0,
      "baseOnBalls": 0,
      "hitByPitch": 0,
      "runs": 0,
      "rbi": 0,
      "strikeouts": 0,
      "plateAppearances": 2,
      "sacBunts": 0,
      "sacFlies": 0,
      "groundIntoDoublePlay": 0,
      "groundIntoTriplePlay": 0,
      "leftOnBase": 0,
      "groundOuts": 1,
      "flyOuts": 0,
      "lineOuts": 0,
      "popOuts": 0,
      "airOuts": 0,
      "catchersInterference": 0,
      "caughtStealing": 0,
      "intentionalWalks": 0,
      "pickoffs": 0,
      "fantasyScore": 1
    },
    {
      "gameDate": "2026-05-18",
      "gamePk": null,
      "atBats": 3,
      "hits": 1,
      "doubles": 0,
      "triples": 0,
      "homeRuns": 0,
      "totalBases": 1,
      "stolenBases": 0,
      "baseOnBalls": 1,
      "hitByPitch": 0,
      "runs": 2,
      "rbi": 4,
      "strikeouts": 1,
      "plateAppearances": 4,
      "sacBunts": 0,
      "sacFlies": 0,
      "groundIntoDoublePlay": 0,
      "groundIntoTriplePlay": 0,
      "leftOnBase": 2,
      "groundOuts": 1,
      "flyOuts": 0,
      "lineOuts": 0,
      "popOuts": 0,
      "airOuts": 0,
      "catchersInterference": 0,
      "caughtStealing": 0,
      "intentionalWalks": 0,
      "pickoffs": 0,
      "fantasyScore": 2
    },
    {
      "gameDate": "2026-05-19",
      "gamePk": null,
      "atBats": 4,
      "hits": 0,
      "doubles": 0,
      "triples": 0,
      "homeRuns": 0,
      "totalBases": 0,
      "stolenBases": 0,
      "baseOnBalls": 0,
      "hitByPitch": 0,
      "runs": 0,
      "rbi": 0,
      "strikeouts": 3,
      "plateAppearances": 4,
      "sacBunts": 0,
      "sacFlies": 0,
      "groundIntoDoublePlay": 0,
      "groundIntoTriplePlay": 0,
      "leftOnBase": 2,
      "groundOuts": 1,
      "flyOuts": 0,
      "lineOuts": 0,
      "popOuts": 0,
      "airOuts": 0,
      "catchersInterference": 0,
      "caughtStealing": 0,
      "intentionalWalks": 0,
      "pickoffs": 0,
      "fantasyScore": 0
    },
    {
      "gameDate": "2026-05-21",
      "gamePk": null,
      "atBats": 1,
      "hits": 0,
      "doubles": 0,
      "triples": 0,
      "homeRuns": 0,
      "totalBases": 0,
      "stolenBases": 0,
      "baseOnBalls": 1,
      "hitByPitch": 0,
      "runs": 0,
      "rbi": 0,
      "strikeouts": 0,
      "plateAppearances": 2,
      "sacBunts": 0,
      "sacFlies": 0,
      "groundIntoDoublePlay": 0,
      "groundIntoTriplePlay": 0,
      "leftOnBase": 0,
      "groundOuts": 1,
      "flyOuts": 0,
      "lineOuts": 0,
      "popOuts": 0,
      "airOuts": 0,
      "catchersInterference": 0,
      "caughtStealing": 0,
      "intentionalWalks": 0,
      "pickoffs": 0,
      "fantasyScore": 1
    },
    {
      "gameDate": "2026-05-22",
      "gamePk": null,
      "atBats": 3,
      "hits": 1,
      "doubles": 0,
      "triples": 0,
      "homeRuns": 0,
      "totalBases": 1,
      "stolenBases": 0,
      "baseOnBalls": 0,
      "hitByPitch": 0,
      "runs": 0,
      "rbi": 0,
      "strikeouts": 0,
      "plateAppearances": 3,
      "sacBunts": 0,
      "sacFlies": 0,
      "groundIntoDoublePlay": 1,
      "groundIntoTriplePlay": 0,
      "leftOnBase": 2,
      "groundOuts": 2,
      "flyOuts": 0,
      "lineOuts": 0,
      "popOuts": 0,
      "airOuts": 0,
      "catchersInterference": 0,
      "caughtStealing": 0,
      "intentionalWalks": 0,
      "pickoffs": 0,
      "fantasyScore": 1
    },
    {
      "gameDate": "2026-05-23",
      "gamePk": null,
      "atBats": 2,
      "hits": 1,
      "doubles": 0,
      "triples": 0,
      "homeRuns": 0,
      "totalBases": 1,
      "stolenBases": 0,
      "baseOnBalls": 1,
      "hitByPitch": 0,
      "runs": 0,
      "rbi": 0,
      "strikeouts": 0,
      "plateAppearances": 3,
      "sacBunts": 0,
      "sacFlies": 0,
      "groundIntoDoublePlay": 0,
      "groundIntoTriplePlay": 0,
      "leftOnBase": 1,
      "groundOuts": 0,
      "flyOuts": 0,
      "lineOuts": 0,
      "popOuts": 1,
      "airOuts": 1,
      "catchersInterference": 0,
      "caughtStealing": 0,
      "intentionalWalks": 0,
      "pickoffs": 0,
      "fantasyScore": 2
    },
    {
      "gameDate": "2026-05-25",
      "gamePk": null,
      "atBats": 4,
      "hits": 1,
      "doubles": 0,
      "triples": 0,
      "homeRuns": 0,
      "totalBases": 1,
      "stolenBases": 0,
      "baseOnBalls": 0,
      "hitByPitch": 0,
      "runs": 0,
      "rbi": 0,
      "strikeouts": 1,
      "plateAppearances": 4,
      "sacBunts": 0,
      "sacFlies": 0,
      "groundIntoDoublePlay": 0,
      "groundIntoTriplePlay": 0,
      "leftOnBase": 1,
      "groundOuts": 1,
      "flyOuts": 0,
      "lineOuts": 0,
      "popOuts": 1,
      "airOuts": 1,
      "catchersInterference": 0,
      "caughtStealing": 0,
      "intentionalWalks": 0,
      "pickoffs": 0,
      "fantasyScore": 1
    },
    {
      "gameDate": "2026-05-26",
      "gamePk": null,
      "atBats": 3,
      "hits": 0,
      "doubles": 0,
      "triples": 0,
      "homeRuns": 0,
      "totalBases": 0,
      "stolenBases": 0,
      "baseOnBalls": 0,
      "hitByPitch": 0,
      "runs": 0,
      "rbi": 0,
      "strikeouts": 0,
      "plateAppearances": 3,
      "sacBunts": 0,
      "sacFlies": 0,
      "groundIntoDoublePlay": 0,
      "groundIntoTriplePlay": 0,
      "leftOnBase": 2,
      "groundOuts": 1,
      "flyOuts": 2,
      "lineOuts": 0,
      "popOuts": 0,
      "airOuts": 2,
      "catchersInterference": 0,
      "caughtStealing": 0,
      "intentionalWalks": 0,
      "pickoffs": 0,
      "fantasyScore": 0
    },
    {
      "gameDate": "2026-05-29",
      "gamePk": null,
      "atBats": 4,
      "hits": 1,
      "doubles": 0,
      "triples": 0,
      "homeRuns": 0,
      "totalBases": 1,
      "stolenBases": 0,
      "baseOnBalls": 0,
      "hitByPitch": 0,
      "runs": 1,
      "rbi": 0,
      "strikeouts": 1,
      "plateAppearances": 4,
      "sacBunts": 0,
      "sacFlies": 0,
      "groundIntoDoublePlay": 0,
      "groundIntoTriplePlay": 0,
      "leftOnBase": 1,
      "groundOuts": 1,
      "flyOuts": 0,
      "lineOuts": 0,
      "popOuts": 1,
      "airOuts": 1,
      "catchersInterference": 0,
      "caughtStealing": 0,
      "intentionalWalks": 0,
      "pickoffs": 0,
      "fantasyScore": 1
    },
    {
      "gameDate": "2026-05-30",
      "gamePk": null,
      "atBats": 3,
      "hits": 0,
      "doubles": 0,
      "triples": 0,
      "homeRuns": 0,
      "totalBases": 0,
      "stolenBases": 0,
      "baseOnBalls": 0,
      "hitByPitch": 0,
      "runs": 0,
      "rbi": 0,
      "strikeouts": 2,
      "plateAppearances": 3,
      "sacBunts": 0,
      "sacFlies": 0,
      "groundIntoDoublePlay": 0,
      "groundIntoTriplePlay": 0,
      "leftOnBase": 1,
      "groundOuts": 0,
      "flyOuts": 1,
      "lineOuts": 0,
      "popOuts": 0,
      "airOuts": 1,
      "catchersInterference": 0,
      "caughtStealing": 0,
      "intentionalWalks": 0,
      "pickoffs": 0,
      "fantasyScore": 0
    },
    {
      "gameDate": "2026-06-01",
      "gamePk": null,
      "atBats": 3,
      "hits": 1,
      "doubles": 0,
      "triples": 0,
      "homeRuns": 0,
      "totalBases": 1,
      "stolenBases": 0,
      "baseOnBalls": 0,
      "hitByPitch": 0,
      "runs": 0,
      "rbi": 0,
      "strikeouts": 0,
      "plateAppearances": 4,
      "sacBunts": 1,
      "sacFlies": 0,
      "groundIntoDoublePlay": 0,
      "groundIntoTriplePlay": 0,
      "leftOnBase": 0,
      "groundOuts": 2,
      "flyOuts": 1,
      "lineOuts": 0,
      "popOuts": 0,
      "airOuts": 1,
      "catchersInterference": 0,
      "caughtStealing": 0,
      "intentionalWalks": 0,
      "pickoffs": 0,
      "fantasyScore": 1
    },
    {
      "gameDate": "2026-06-02",
      "gamePk": null,
      "atBats": 3,
      "hits": 1,
      "doubles": 0,
      "triples": 0,
      "homeRuns": 1,
      "totalBases": 4,
      "stolenBases": 0,
      "baseOnBalls": 0,
      "hitByPitch": 0,
      "runs": 1,
      "rbi": 3,
      "strikeouts": 2,
      "plateAppearances": 4,
      "sacBunts": 1,
      "sacFlies": 0,
      "groundIntoDoublePlay": 0,
      "groundIntoTriplePlay": 0,
      "leftOnBase": 3,
      "groundOuts": 1,
      "flyOuts": 0,
      "lineOuts": 0,
      "popOuts": 0,
      "airOuts": 0,
      "catchersInterference": 0,
      "caughtStealing": 0,
      "intentionalWalks": 0,
      "pickoffs": 0,
      "fantasyScore": 4
    },
    {
      "gameDate": "2026-06-03",
      "gamePk": null,
      "atBats": 3,
      "hits": 2,
      "doubles": 0,
      "triples": 0,
      "homeRuns": 0,
      "totalBases": 2,
      "stolenBases": 0,
      "baseOnBalls": 1,
      "hitByPitch": 0,
      "runs": 0,
      "rbi": 2,
      "strikeouts": 0,
      "plateAppearances": 4,
      "sacBunts": 0,
      "sacFlies": 0,
      "groundIntoDoublePlay": 0,
      "groundIntoTriplePlay": 0,
      "leftOnBase": 1,
      "groundOuts": 1,
      "flyOuts": 0,
      "lineOuts": 0,
      "popOuts": 0,
      "airOuts": 0,
      "catchersInterference": 0,
      "caughtStealing": 0,
      "intentionalWalks": 0,
      "pickoffs": 0,
      "fantasyScore": 3
    },
    {
      "gameDate": "2026-06-05",
      "gamePk": null,
      "atBats": 3,
      "hits": 0,
      "doubles": 0,
      "triples": 0,
      "homeRuns": 0,
      "totalBases": 0,
      "stolenBases": 0,
      "baseOnBalls": 0,
      "hitByPitch": 0,
      "runs": 0,
      "rbi": 0,
      "strikeouts": 1,
      "plateAppearances": 3,
      "sacBunts": 0,
      "sacFlies": 0,
      "groundIntoDoublePlay": 0,
      "groundIntoTriplePlay": 0,
      "leftOnBase": 1,
      "groundOuts": 1,
      "flyOuts": 1,
      "lineOuts": 0,
      "popOuts": 0,
      "airOuts": 1,
      "catchersInterference": 0,
      "caughtStealing": 0,
      "intentionalWalks": 0,
      "pickoffs": 0,
      "fantasyScore": 0
    },
    {
      "gameDate": "2026-06-06",
      "gamePk": null,
      "atBats": 4,
      "hits": 1,
      "doubles": 1,
      "triples": 0,
      "homeRuns": 0,
      "totalBases": 2,
      "stolenBases": 0,
      "baseOnBalls": 0,
      "hitByPitch": 0,
      "runs": 0,
      "rbi": 1,
      "strikeouts": 1,
      "plateAppearances": 4,
      "sacBunts": 0,
      "sacFlies": 0,
      "groundIntoDoublePlay": 1,
      "groundIntoTriplePlay": 0,
      "leftOnBase": 4,
      "groundOuts": 2,
      "flyOuts": 0,
      "lineOuts": 0,
      "popOuts": 0,
      "airOuts": 0,
      "catchersInterference": 0,
      "caughtStealing": 0,
      "intentionalWalks": 0,
      "pickoffs": 0,
      "fantasyScore": 2
    },
    {
      "gameDate": "2026-06-07",
      "gamePk": null,
      "atBats": 3,
      "hits": 0,
      "doubles": 0,
      "triples": 0,
      "homeRuns": 0,
      "totalBases": 0,
      "stolenBases": 0,
      "baseOnBalls": 0,
      "hitByPitch": 0,
      "runs": 0,
      "rbi": 1,
      "strikeouts": 2,
      "plateAppearances": 3,
      "sacBunts": 0,
      "sacFlies": 0,
      "groundIntoDoublePlay": 0,
      "groundIntoTriplePlay": 0,
      "leftOnBase": 1,
      "groundOuts": 1,
      "flyOuts": 0,
      "lineOuts": 0,
      "popOuts": 0,
      "airOuts": 0,
      "catchersInterference": 0,
      "caughtStealing": 0,
      "intentionalWalks": 0,
      "pickoffs": 0,
      "fantasyScore": 0
    },
    {
      "gameDate": "2026-06-09",
      "gamePk": null,
      "atBats": 4,
      "hits": 4,
      "doubles": 0,
      "triples": 0,
      "homeRuns": 0,
      "totalBases": 4,
      "stolenBases": 0,
      "baseOnBalls": 0,
      "hitByPitch": 0,
      "runs": 3,
      "rbi": 0,
      "strikeouts": 0,
      "plateAppearances": 4,
      "sacBunts": 0,
      "sacFlies": 0,
      "groundIntoDoublePlay": 0,
      "groundIntoTriplePlay": 0,
      "leftOnBase": 0,
      "groundOuts": 0,
      "flyOuts": 0,
      "lineOuts": 0,
      "popOuts": 0,
      "airOuts": 0,
      "catchersInterference": 0,
      "caughtStealing": 0,
      "intentionalWalks": 0,
      "pickoffs": 0,
      "fantasyScore": 4
    },
    {
      "gameDate": "2026-06-11",
      "gamePk": null,
      "atBats": 3,
      "hits": 0,
      "doubles": 0,
      "triples": 0,
      "homeRuns": 0,
      "totalBases": 0,
      "stolenBases": 0,
      "baseOnBalls": 0,
      "hitByPitch": 0,
      "runs": 0,
      "rbi": 0,
      "strikeouts": 1,
      "plateAppearances": 3,
      "sacBunts": 0,
      "sacFlies": 0,
      "groundIntoDoublePlay": 0,
      "groundIntoTriplePlay": 0,
      "leftOnBase": 3,
      "groundOuts": 1,
      "flyOuts": 1,
      "lineOuts": 0,
      "popOuts": 0,
      "airOuts": 1,
      "catchersInterference": 0,
      "caughtStealing": 0,
      "intentionalWalks": 0,
      "pickoffs": 0,
      "fantasyScore": 0
    },
    {
      "gameDate": "2026-06-12",
      "gamePk": null,
      "atBats": 3,
      "hits": 0,
      "doubles": 0,
      "triples": 0,
      "homeRuns": 0,
      "totalBases": 0,
      "stolenBases": 0,
      "baseOnBalls": 1,
      "hitByPitch": 0,
      "runs": 0,
      "rbi": 0,
      "strikeouts": 1,
      "plateAppearances": 4,
      "sacBunts": 0,
      "sacFlies": 0,
      "groundIntoDoublePlay": 0,
      "groundIntoTriplePlay": 0,
      "leftOnBase": 3,
      "groundOuts": 0,
      "flyOuts": 1,
      "lineOuts": 0,
      "popOuts": 1,
      "airOuts": 2,
      "catchersInterference": 0,
      "caughtStealing": 0,
      "intentionalWalks": 0,
      "pickoffs": 0,
      "fantasyScore": 1
    },
    {
      "gameDate": "2026-06-14",
      "gamePk": null,
      "atBats": 3,
      "hits": 1,
      "doubles": 0,
      "triples": 0,
      "homeRuns": 1,
      "totalBases": 4,
      "stolenBases": 0,
      "baseOnBalls": 1,
      "hitByPitch": 0,
      "runs": 1,
      "rbi": 1,
      "strikeouts": 0,
      "plateAppearances": 4,
      "sacBunts": 0,
      "sacFlies": 0,
      "groundIntoDoublePlay": 0,
      "groundIntoTriplePlay": 0,
      "leftOnBase": 0,
      "groundOuts": 1,
      "flyOuts": 0,
      "lineOuts": 0,
      "popOuts": 1,
      "airOuts": 1,
      "catchersInterference": 0,
      "caughtStealing": 0,
      "intentionalWalks": 0,
      "pickoffs": 0,
      "fantasyScore": 5
    },
    {
      "gameDate": "2026-06-15",
      "gamePk": null,
      "atBats": 1,
      "hits": 1,
      "doubles": 1,
      "triples": 0,
      "homeRuns": 0,
      "totalBases": 2,
      "stolenBases": 0,
      "baseOnBalls": 1,
      "hitByPitch": 0,
      "runs": 0,
      "rbi": 0,
      "strikeouts": 0,
      "plateAppearances": 2,
      "sacBunts": 0,
      "sacFlies": 0,
      "groundIntoDoublePlay": 0,
      "groundIntoTriplePlay": 0,
      "leftOnBase": 0,
      "groundOuts": 0,
      "flyOuts": 0,
      "lineOuts": 0,
      "popOuts": 0,
      "airOuts": 0,
      "catchersInterference": 0,
      "caughtStealing": 0,
      "intentionalWalks": 0,
      "pickoffs": 0,
      "fantasyScore": 3
    },
    {
      "gameDate": "2026-06-17",
      "gamePk": null,
      "atBats": 3,
      "hits": 2,
      "doubles": 0,
      "triples": 0,
      "homeRuns": 1,
      "totalBases": 5,
      "stolenBases": 0,
      "baseOnBalls": 1,
      "hitByPitch": 1,
      "runs": 3,
      "rbi": 2,
      "strikeouts": 0,
      "plateAppearances": 5,
      "sacBunts": 0,
      "sacFlies": 0,
      "groundIntoDoublePlay": 0,
      "groundIntoTriplePlay": 0,
      "leftOnBase": 0,
      "groundOuts": 0,
      "flyOuts": 1,
      "lineOuts": 0,
      "popOuts": 0,
      "airOuts": 1,
      "catchersInterference": 0,
      "caughtStealing": 0,
      "intentionalWalks": 0,
      "pickoffs": 0,
      "fantasyScore": 7
    },
    {
      "gameDate": "2026-06-19",
      "gamePk": null,
      "atBats": 2,
      "hits": 0,
      "doubles": 0,
      "triples": 0,
      "homeRuns": 0,
      "totalBases": 0,
      "stolenBases": 0,
      "baseOnBalls": 0,
      "hitByPitch": 0,
      "runs": 0,
      "rbi": 0,
      "strikeouts": 0,
      "plateAppearances": 2,
      "sacBunts": 0,
      "sacFlies": 0,
      "groundIntoDoublePlay": 0,
      "groundIntoTriplePlay": 0,
      "leftOnBase": 2,
      "groundOuts": 2,
      "flyOuts": 0,
      "lineOuts": 0,
      "popOuts": 0,
      "airOuts": 0,
      "catchersInterference": 0,
      "caughtStealing": 0,
      "intentionalWalks": 0,
      "pickoffs": 0,
      "fantasyScore": 0
    },
    {
      "gameDate": "2026-06-20",
      "gamePk": null,
      "atBats": 4,
      "hits": 1,
      "doubles": 0,
      "triples": 0,
      "homeRuns": 0,
      "totalBases": 1,
      "stolenBases": 0,
      "baseOnBalls": 0,
      "hitByPitch": 0,
      "runs": 1,
      "rbi": 0,
      "strikeouts": 0,
      "plateAppearances": 4,
      "sacBunts": 0,
      "sacFlies": 0,
      "groundIntoDoublePlay": 0,
      "groundIntoTriplePlay": 0,
      "leftOnBase": 3,
      "groundOuts": 1,
      "flyOuts": 1,
      "lineOuts": 1,
      "popOuts": 0,
      "airOuts": 2,
      "catchersInterference": 0,
      "caughtStealing": 0,
      "intentionalWalks": 0,
      "pickoffs": 0,
      "fantasyScore": 1
    },
    {
      "gameDate": "2026-06-21",
      "gamePk": null,
      "atBats": 3,
      "hits": 0,
      "doubles": 0,
      "triples": 0,
      "homeRuns": 0,
      "totalBases": 0,
      "stolenBases": 0,
      "baseOnBalls": 0,
      "hitByPitch": 0,
      "runs": 0,
      "rbi": 0,
      "strikeouts": 1,
      "plateAppearances": 3,
      "sacBunts": 0,
      "sacFlies": 0,
      "groundIntoDoublePlay": 0,
      "groundIntoTriplePlay": 0,
      "leftOnBase": 1,
      "groundOuts": 1,
      "flyOuts": 1,
      "lineOuts": 0,
      "popOuts": 0,
      "airOuts": 1,
      "catchersInterference": 0,
      "caughtStealing": 0,
      "intentionalWalks": 0,
      "pickoffs": 0,
      "fantasyScore": 0
    },
    {
      "gameDate": "2026-06-22",
      "gamePk": null,
      "atBats": 3,
      "hits": 1,
      "doubles": 0,
      "triples": 0,
      "homeRuns": 0,
      "totalBases": 1,
      "stolenBases": 0,
      "baseOnBalls": 0,
      "hitByPitch": 0,
      "runs": 1,
      "rbi": 0,
      "strikeouts": 2,
      "plateAppearances": 3,
      "sacBunts": 0,
      "sacFlies": 0,
      "groundIntoDoublePlay": 0,
      "groundIntoTriplePlay": 0,
      "leftOnBase": 0,
      "groundOuts": 0,
      "flyOuts": 0,
      "lineOuts": 0,
      "popOuts": 0,
      "airOuts": 0,
      "catchersInterference": 0,
      "caughtStealing": 0,
      "intentionalWalks": 0,
      "pickoffs": 0,
      "fantasyScore": 1
    },
    {
      "gameDate": "2026-06-23",
      "gamePk": null,
      "atBats": 4,
      "hits": 2,
      "doubles": 0,
      "triples": 0,
      "homeRuns": 1,
      "totalBases": 5,
      "stolenBases": 0,
      "baseOnBalls": 0,
      "hitByPitch": 0,
      "runs": 1,
      "rbi": 2,
      "strikeouts": 0,
      "plateAppearances": 4,
      "sacBunts": 0,
      "sacFlies": 0,
      "groundIntoDoublePlay": 0,
      "groundIntoTriplePlay": 0,
      "leftOnBase": 1,
      "groundOuts": 0,
      "flyOuts": 0,
      "lineOuts": 2,
      "popOuts": 0,
      "airOuts": 2,
      "catchersInterference": 0,
      "caughtStealing": 0,
      "intentionalWalks": 0,
      "pickoffs": 0,
      "fantasyScore": 5
    },
    {
      "gameDate": "2026-06-26",
      "gamePk": null,
      "atBats": 3,
      "hits": 0,
      "doubles": 0,
      "triples": 0,
      "homeRuns": 0,
      "totalBases": 0,
      "stolenBases": 0,
      "baseOnBalls": 1,
      "hitByPitch": 0,
      "runs": 1,
      "rbi": 0,
      "strikeouts": 0,
      "plateAppearances": 4,
      "sacBunts": 0,
      "sacFlies": 0,
      "groundIntoDoublePlay": 1,
      "groundIntoTriplePlay": 0,
      "leftOnBase": 1,
      "groundOuts": 3,
      "flyOuts": 0,
      "lineOuts": 0,
      "popOuts": 0,
      "airOuts": 0,
      "catchersInterference": 0,
      "caughtStealing": 0,
      "intentionalWalks": 0,
      "pickoffs": 0,
      "fantasyScore": 1
    },
    {
      "gameDate": "2026-06-27",
      "gamePk": null,
      "atBats": 4,
      "hits": 1,
      "doubles": 0,
      "triples": 0,
      "homeRuns": 0,
      "totalBases": 1,
      "stolenBases": 0,
      "baseOnBalls": 0,
      "hitByPitch": 0,
      "runs": 1,
      "rbi": 0,
      "strikeouts": 1,
      "plateAppearances": 4,
      "sacBunts": 0,
      "sacFlies": 0,
      "groundIntoDoublePlay": 1,
      "groundIntoTriplePlay": 0,
      "leftOnBase": 3,
      "groundOuts": 1,
      "flyOuts": 1,
      "lineOuts": 0,
      "popOuts": 0,
      "airOuts": 1,
      "catchersInterference": 0,
      "caughtStealing": 0,
      "intentionalWalks": 0,
      "pickoffs": 0,
      "fantasyScore": 1
    },
    {
      "gameDate": "2026-06-28",
      "gamePk": null,
      "atBats": 1,
      "hits": 0,
      "doubles": 0,
      "triples": 0,
      "homeRuns": 0,
      "totalBases": 0,
      "stolenBases": 0,
      "baseOnBalls": 0,
      "hitByPitch": 0,
      "runs": 0,
      "rbi": 0,
      "strikeouts": 0,
      "plateAppearances": 1,
      "sacBunts": 0,
      "sacFlies": 0,
      "groundIntoDoublePlay": 1,
      "groundIntoTriplePlay": 0,
      "leftOnBase": 1,
      "groundOuts": 1,
      "flyOuts": 0,
      "lineOuts": 0,
      "popOuts": 0,
      "airOuts": 0,
      "catchersInterference": 0,
      "caughtStealing": 0,
      "intentionalWalks": 0,
      "pickoffs": 0,
      "fantasyScore": 0
    },
    {
      "gameDate": "2026-06-29",
      "gamePk": null,
      "atBats": 4,
      "hits": 1,
      "doubles": 0,
      "triples": 0,
      "homeRuns": 0,
      "totalBases": 1,
      "stolenBases": 0,
      "baseOnBalls": 0,
      "hitByPitch": 0,
      "runs": 0,
      "rbi": 1,
      "strikeouts": 0,
      "plateAppearances": 4,
      "sacBunts": 0,
      "sacFlies": 0,
      "groundIntoDoublePlay": 0,
      "groundIntoTriplePlay": 0,
      "leftOnBase": 3,
      "groundOuts": 0,
      "flyOuts": 3,
      "lineOuts": 0,
      "popOuts": 0,
      "airOuts": 3,
      "catchersInterference": 0,
      "caughtStealing": 0,
      "intentionalWalks": 0,
      "pickoffs": 0,
      "fantasyScore": 1
    },
    {
      "gameDate": "2026-06-30",
      "gamePk": null,
      "atBats": 4,
      "hits": 1,
      "doubles": 0,
      "triples": 0,
      "homeRuns": 1,
      "totalBases": 4,
      "stolenBases": 0,
      "baseOnBalls": 0,
      "hitByPitch": 0,
      "runs": 1,
      "rbi": 2,
      "strikeouts": 1,
      "plateAppearances": 4,
      "sacBunts": 0,
      "sacFlies": 0,
      "groundIntoDoublePlay": 0,
      "groundIntoTriplePlay": 0,
      "leftOnBase": 1,
      "groundOuts": 0,
      "flyOuts": 2,
      "lineOuts": 0,
      "popOuts": 0,
      "airOuts": 2,
      "catchersInterference": 0,
      "caughtStealing": 0,
      "intentionalWalks": 0,
      "pickoffs": 0,
      "fantasyScore": 4
    },
    {
      "gameDate": "2026-07-01",
      "gamePk": null,
      "atBats": 1,
      "hits": 1,
      "doubles": 0,
      "triples": 0,
      "homeRuns": 1,
      "totalBases": 4,
      "stolenBases": 0,
      "baseOnBalls": 0,
      "hitByPitch": 0,
      "runs": 1,
      "rbi": 1,
      "strikeouts": 0,
      "plateAppearances": 1,
      "sacBunts": 0,
      "sacFlies": 0,
      "groundIntoDoublePlay": 0,
      "groundIntoTriplePlay": 0,
      "leftOnBase": 0,
      "groundOuts": 0,
      "flyOuts": 0,
      "lineOuts": 0,
      "popOuts": 0,
      "airOuts": 0,
      "catchersInterference": 0,
      "caughtStealing": 0,
      "intentionalWalks": 0,
      "pickoffs": 0,
      "fantasyScore": 4
    }
  ],
  "navigation": {
    "prevSlug": "joc-pederson",
    "prevName": "Joc Pederson",
    "nextSlug": "joey-bart",
    "nextName": "Joey Bart"
  }
}